folklore/__init__.py
folklore/_compat.py
folklore/exc.py
folklore/log.py
folklore/service.py
folklore/testing.py
folklore/hook/__init__.py
folklore/hook/api.py
folklore-0.2.0.dist-info/LICENSE
folklore-0.2.0.dist-info/METADATA
folklore-0.2.0.dist-info/WHEEL
folklore-0.2.0.dist-info/top_level.txt
folklore-0.2.0.dist-info/RECORD
