Metadata-Version: 2.1
Name: folklore
Version: 0.2.0
Summary: An elegant thrift service development framework
Home-page: https://github.com/maralla/folklore
Author: maralla
Author-email: maralla.ai@gmail.com
License: UNKNOWN
Platform: UNKNOWN
Requires-Dist: folklore-config
Requires-Dist: folklore-thrift
Requires-Dist: thriftpy (>=0.3.9)
Requires-Dist: gevent (>=1.2.1)
